chess_scraping/__init__.py
chess_scraping/__init__.pyi
chess_scraping/_types.py
chess_scraping/scrape.py
chess_scraping/asso_fr/__init__.py
chess_scraping/asso_fr/__init__.pyi
chess_scraping/asso_fr/download.py
chess_scraping/asso_fr/parse.py
chess_scraping/asso_fr/scrape.py
chess_scraping/belgium_bic/__init__.py
chess_scraping/belgium_bic/__init__.pyi
chess_scraping/belgium_bic/download.py
chess_scraping/belgium_bic/parse.py
chess_scraping/belgium_bic/scrape.py
chess_scraping/chess_manager/__init__.py
chess_scraping/chess_manager/__init__.pyi
chess_scraping/chess_manager/download.py
chess_scraping/chess_manager/parse.py
chess_scraping/chess_manager/scrape.py
chess_scraping/chess_results/__init__.py
chess_scraping/chess_results/__init__.pyi
chess_scraping/chess_results/download.py
chess_scraping/chess_results/scrape.py
chess_scraping/chess_results/parse/__init__.py
chess_scraping/chess_results/parse/common.py
chess_scraping/chess_results/parse/parse.py
chess_scraping/chess_results/parse/single_robin.py
chess_scraping/chess_results/parse/single_swiss.py
chess_scraping/chess_results/parse/system.py
chess_scraping/info64/__init__.py
chess_scraping/info64/__init__.pyi
chess_scraping/info64/download.py
chess_scraping/info64/parse.py
chess_scraping/info64/scrape.py
chess_scraping/util/__init__.py
chess_scraping/util/__init__.pyi
chess_scraping/util/util.py
chess_scraping-0.3.2.dist-info/METADATA
chess_scraping-0.3.2.dist-info/WHEEL
chess_scraping-0.3.2.dist-info/top_level.txt
chess_scraping-0.3.2.dist-info/RECORD
